{
  "data": {
    "SpatialArea.QuantitativeAccuracyBandID": null,
    "Description": "Wellbore Marker",
    "ResourceLifecycleStatus": null,
    "SpatialArea.SpatialParameterTypeID": null,
    "ResourceCurationStatus": null,
    "TechnicalAssuranceID": null,
    "SpatialArea.SpatialGeometryTypeID": null,
    "Source": null,
    "IsExtendedLoad": null,
    "Name": "1676.csv",
    "Datasets": [
      "contoso-data:dataset--File.Generic:76679c28-bc22-4827-a4d7-8c3515dd4826:1678349580265230"
    ],
    "VerticalMeasurement.VerticalCRSID": null,
    "VerticalMeasurement.VerticalMeasurementTypeID": null,
    "SpatialPoint.CoordinateQualityCheckPerformedBy": null,
    "ResourceSecurityClassification": "contoso-data:reference-data--ResourceSecurityClassification:RESTRICTED:",
    "VerticalMeasurement.WellboreTVDTrajectoryID": null,
    "VerticalMeasurement.VerticalMeasurementPathID": null,
    "ExistenceKind": null,
    "VerticalMeasurement.VerticalMeasurementDescription": null,
    "SpatialPoint.SpatialParameterTypeID": null,
    "Markers": [
      {
        "Missing": null,
        "MarkerMeasuredDepth": 0.0,
        "FeatureTypeID": null,
        "MarkerTypeID": null,
        "GeologicalAge": null,
        "MarkerInterpreter": null,
        "MarkerName": "QUATER. UNDIFF.",
        "FeatureName": null
      },
      {
        "Missing": null,
        "MarkerMeasuredDepth": 100.0,
        "FeatureTypeID": null,
        "MarkerTypeID": null,
        "GeologicalAge": null,
        "MarkerInterpreter": null,
        "MarkerName": "Maassluis Formation",
        "FeatureName": null
      },
      {
        "Missing": null,
        "MarkerMeasuredDepth": 220.0,
        "FeatureTypeID": null,
        "MarkerTypeID": null,
        "GeologicalAge": null,
        "MarkerInterpreter": null,
        "MarkerName": "Breda Formation",
        "FeatureName": null
      },
      {
        "Missing": null,
        "MarkerMeasuredDepth": 427.0,
        "FeatureTypeID": null,
        "MarkerTypeID": null,
        "GeologicalAge": null,
        "MarkerInterpreter": null,
        "MarkerName": "Veldhoven Clay Member",
        "FeatureName": null
      },
      {
        "Missing": null,
        "MarkerMeasuredDepth": 520.0,
        "FeatureTypeID": null,
        "MarkerTypeID": null,
        "GeologicalAge": null,
        "MarkerInterpreter": null,
        "MarkerName": "Voort Member",
        "FeatureName": null
      },
      {
        "Missing": null,
        "MarkerMeasuredDepth": 536.0,
        "FeatureTypeID": null,
        "MarkerTypeID": null,
        "GeologicalAge": null,
        "MarkerInterpreter": null,
        "MarkerName": "Rupel Clay Member",
        "FeatureName": null
      },
      {
        "Missing": null,
        "MarkerMeasuredDepth": 632.0,
        "FeatureTypeID": null,
        "MarkerTypeID": null,
        "GeologicalAge": null,
        "MarkerInterpreter": null,
        "MarkerName": "VESSEM MB",
        "FeatureName": null
      },
      {
        "Missing": null,
        "MarkerMeasuredDepth": 637.0,
        "FeatureTypeID": null,
        "MarkerTypeID": null,
        "GeologicalAge": null,
        "MarkerInterpreter": null,
        "MarkerName": "Landen Clay Member",
        "FeatureName": null
      },
      {
        "Missing": null,
        "MarkerMeasuredDepth": 683.0,
        "FeatureTypeID": null,
        "MarkerTypeID": null,
        "GeologicalAge": null,
        "MarkerInterpreter": null,
        "MarkerName": "Heers Member",
        "FeatureName": null
      },
      {
        "Missing": null,
        "MarkerMeasuredDepth": 693.0,
        "FeatureTypeID": null,
        "MarkerTypeID": null,
        "GeologicalAge": null,
        "MarkerInterpreter": null,
        "MarkerName": "Ommelanden Formation",
        "FeatureName": null
      },
      {
        "Missing": null,
        "MarkerMeasuredDepth": 700.0,
        "FeatureTypeID": null,
        "MarkerTypeID": null,
        "GeologicalAge": null,
        "MarkerInterpreter": null,
        "MarkerName": "Texel Formation",
        "FeatureName": null
      },
      {
        "Missing": null,
        "MarkerMeasuredDepth": 780.0,
        "FeatureTypeID": null,
        "MarkerTypeID": null,
        "GeologicalAge": null,
        "MarkerInterpreter": null,
        "MarkerName": "Upper Holland Marl Member",
        "FeatureName": null
      },
      {
        "Missing": null,
        "MarkerMeasuredDepth": 796.0,
        "FeatureTypeID": null,
        "MarkerTypeID": null,
        "GeologicalAge": null,
        "MarkerInterpreter": null,
        "MarkerName": "Middle Holland Claystone Member",
        "FeatureName": null
      },
      {
        "Missing": null,
        "MarkerMeasuredDepth": 818.0,
        "FeatureTypeID": null,
        "MarkerTypeID": null,
        "GeologicalAge": null,
        "MarkerInterpreter": null,
        "MarkerName": "Holland Greensand Member",
        "FeatureName": null
      },
      {
        "Missing": null,
        "MarkerMeasuredDepth": 837.0,
        "FeatureTypeID": null,
        "MarkerTypeID": null,
        "GeologicalAge": null,
        "MarkerInterpreter": null,
        "MarkerName": "Lower Holland Marl Member",
        "FeatureName": null
      },
      {
        "Missing": null,
        "MarkerMeasuredDepth": 889.0,
        "FeatureTypeID": null,
        "MarkerTypeID": null,
        "GeologicalAge": null,
        "MarkerInterpreter": null,
        "MarkerName": "Main Claystone Member",
        "FeatureName": null
      },
      {
        "Missing": null,
        "MarkerMeasuredDepth": 984.5,
        "FeatureTypeID": null,
        "MarkerTypeID": null,
        "GeologicalAge": null,
        "MarkerInterpreter": null,
        "MarkerName": "Zechstein Upper Claystone Formation",
        "FeatureName": null
      },
      {
        "Missing": null,
        "MarkerMeasuredDepth": 996.0,
        "FeatureTypeID": null,
        "MarkerTypeID": null,
        "GeologicalAge": null,
        "MarkerInterpreter": null,
        "MarkerName": "Z4 Pegmatite Anhydrite Member",
        "FeatureName": null
      },
      {
        "Missing": null,
        "MarkerMeasuredDepth": 998.0,
        "FeatureTypeID": null,
        "MarkerTypeID": null,
        "GeologicalAge": null,
        "MarkerInterpreter": null,
        "MarkerName": "Red Salt Clay Member",
        "FeatureName": null
      },
      {
        "Missing": null,
        "MarkerMeasuredDepth": 1008.0,
        "FeatureTypeID": null,
        "MarkerTypeID": null,
        "GeologicalAge": null,
        "MarkerInterpreter": null,
        "MarkerName": "Z3 Carbonate Member",
        "FeatureName": null
      },
      {
        "Missing": null,
        "MarkerMeasuredDepth": 1018.0,
        "FeatureTypeID": null,
        "MarkerTypeID": null,
        "GeologicalAge": null,
        "MarkerInterpreter": null,
        "MarkerName": "Grey Salt Clay Member",
        "FeatureName": null
      },
      {
        "Missing": null,
        "MarkerMeasuredDepth": 1019.0,
        "FeatureTypeID": null,
        "MarkerTypeID": null,
        "GeologicalAge": null,
        "MarkerInterpreter": null,
        "MarkerName": "Z2 Middle Claystone Member",
        "FeatureName": null
      },
      {
        "Missing": null,
        "MarkerMeasuredDepth": 1046.0,
        "FeatureTypeID": null,
        "MarkerTypeID": null,
        "GeologicalAge": null,
        "MarkerInterpreter": null,
        "MarkerName": "Z1 Middle Claystone Member",
        "FeatureName": null
      },
      {
        "Missing": null,
        "MarkerMeasuredDepth": 1058.0,
        "FeatureTypeID": null,
        "MarkerTypeID": null,
        "GeologicalAge": null,
        "MarkerInterpreter": null,
        "MarkerName": "Z1 Fringe Carbonate Member",
        "FeatureName": null
      },
      {
        "Missing": null,
        "MarkerMeasuredDepth": 1092.0,
        "FeatureTypeID": null,
        "MarkerTypeID": null,
        "GeologicalAge": null,
        "MarkerInterpreter": null,
        "MarkerName": "Z1 Lower Claystone Member",
        "FeatureName": null
      },
      {
        "Missing": null,
        "MarkerMeasuredDepth": 1100.0,
        "FeatureTypeID": null,
        "MarkerTypeID": null,
        "GeologicalAge": null,
        "MarkerInterpreter": null,
        "MarkerName": "Coppershale Member",
        "FeatureName": null
      },
      {
        "Missing": null,
        "MarkerMeasuredDepth": 1101.0,
        "FeatureTypeID": null,
        "MarkerTypeID": null,
        "GeologicalAge": null,
        "MarkerInterpreter": null,
        "MarkerName": "Slochteren Formation",
        "FeatureName": null
      },
      {
        "Missing": null,
        "MarkerMeasuredDepth": 1119.5,
        "FeatureTypeID": null,
        "MarkerTypeID": null,
        "GeologicalAge": null,
        "MarkerInterpreter": null,
        "MarkerName": "Maurits Formation",
        "FeatureName": null
      }
    ],
    "WellboreID": "contoso-data:master-data--Wellbore:1676:",
    "VerticalMeasurement.VerticalMeasurementUnitOfMeasureID": null,
    "SpatialPoint.QuantitativeAccuracyBandID": null,
    "SpatialArea.QualitativeSpatialAccuracyTypeID": null,
    "SpatialArea.CoordinateQualityCheckPerformedBy": null,
    "VerticalMeasurement.VerticalReferenceEntityID": null,
    "SpatialPoint.SpatialGeometryTypeID": null,
    "ResourceHomeRegionID": null,
    "VerticalMeasurement.VerticalMeasurementSourceID": null,
    "IsDiscoverable": null,
    "VerticalMeasurement.VerticalReferenceID": null,
    "SubmitterName": null,
    "SpatialPoint.QualitativeSpatialAccuracyTypeID": null
  },
  "kind": "osdu:wks:work-product-component--WellboreMarkerSet:1.0.0",
  "source": "wks",
  "acl": {
    "viewers": [
      "data.default.viewers@contoso-data.dataservices.energy"
    ],
    "owners": [
      "data.default.owners@contoso-data.dataservices.energy"
    ]
  },
  "type": "work-product-component--WellboreMarkerSet",
  "version": 1678351838359553,
  "tags": null,
  "createTime": "2023-03-09T08:50:38.365Z",
  "authority": "osdu",
  "namespace": "osdu:wks",
  "legal": {
    "legaltags": [
      "contoso-data-open-test-data"
    ],
    "otherRelevantDataCountries": [
      "US"
    ],
    "status": "compliant"
  },
  "createUser": "a9b01ec8-23d6-41c6-8773-89cf40351b9a",
  "id": "contoso-data:work-product-component--WellboreMarkerSet:38af462bf73348ccb2ee5486132911f9"
}