{
  "data": {
    "SpatialArea.QuantitativeAccuracyBandID": null,
    "Description": "Wellbore Marker",
    "ResourceLifecycleStatus": null,
    "SpatialArea.SpatialParameterTypeID": null,
    "ResourceCurationStatus": null,
    "TechnicalAssuranceID": null,
    "SpatialArea.SpatialGeometryTypeID": null,
    "Source": null,
    "IsExtendedLoad": null,
    "Name": "7652.csv",
    "Datasets": [
      "contoso-data:dataset--File.Generic:2ec8d2c8-0e4b-4744-a287-f1fd315a0061:1678349763059592"
    ],
    "VerticalMeasurement.VerticalCRSID": null,
    "VerticalMeasurement.VerticalMeasurementTypeID": null,
    "SpatialPoint.CoordinateQualityCheckPerformedBy": null,
    "ResourceSecurityClassification": "contoso-data:reference-data--ResourceSecurityClassification:RESTRICTED:",
    "VerticalMeasurement.WellboreTVDTrajectoryID": null,
    "VerticalMeasurement.VerticalMeasurementPathID": null,
    "ExistenceKind": null,
    "VerticalMeasurement.VerticalMeasurementDescription": null,
    "SpatialPoint.SpatialParameterTypeID": null,
    "Markers": [
      {
        "Missing": null,
        "MarkerMeasuredDepth": 0.0,
        "FeatureTypeID": null,
        "MarkerTypeID": null,
        "GeologicalAge": null,
        "MarkerInterpreter": null,
        "MarkerName": "North Sea Supergroup",
        "FeatureName": null
      },
      {
        "Missing": null,
        "MarkerMeasuredDepth": 910.0,
        "FeatureTypeID": null,
        "MarkerTypeID": null,
        "GeologicalAge": null,
        "MarkerInterpreter": null,
        "MarkerName": "Ommelanden Formation",
        "FeatureName": null
      },
      {
        "Missing": null,
        "MarkerMeasuredDepth": 1551.0,
        "FeatureTypeID": null,
        "MarkerTypeID": null,
        "GeologicalAge": null,
        "MarkerInterpreter": null,
        "MarkerName": "Texel Marlstone Member",
        "FeatureName": null
      },
      {
        "Missing": null,
        "MarkerMeasuredDepth": 1717.8,
        "FeatureTypeID": null,
        "MarkerTypeID": null,
        "GeologicalAge": null,
        "MarkerInterpreter": null,
        "MarkerName": "Upper Holland Marl Member",
        "FeatureName": null
      },
      {
        "Missing": null,
        "MarkerMeasuredDepth": 1944.0,
        "FeatureTypeID": null,
        "MarkerTypeID": null,
        "GeologicalAge": null,
        "MarkerInterpreter": null,
        "MarkerName": "Middle Holland Claystone Member",
        "FeatureName": null
      },
      {
        "Missing": null,
        "MarkerMeasuredDepth": 1995.7,
        "FeatureTypeID": null,
        "MarkerTypeID": null,
        "GeologicalAge": null,
        "MarkerInterpreter": null,
        "MarkerName": "Lower Holland Marl Member",
        "FeatureName": null
      },
      {
        "Missing": null,
        "MarkerMeasuredDepth": 2012.0,
        "FeatureTypeID": null,
        "MarkerTypeID": null,
        "GeologicalAge": null,
        "MarkerInterpreter": null,
        "MarkerName": "Vlieland Claystone Formation",
        "FeatureName": null
      },
      {
        "Missing": null,
        "MarkerMeasuredDepth": 2237.5,
        "FeatureTypeID": null,
        "MarkerTypeID": null,
        "GeologicalAge": null,
        "MarkerInterpreter": null,
        "MarkerName": "Kotter Member",
        "FeatureName": null
      },
      {
        "Missing": null,
        "MarkerMeasuredDepth": 2271.6,
        "FeatureTypeID": null,
        "MarkerTypeID": null,
        "GeologicalAge": null,
        "MarkerInterpreter": null,
        "MarkerName": "Aalburg Formation",
        "FeatureName": null
      }
    ],
    "WellboreID": "contoso-data:master-data--Wellbore:7652:",
    "VerticalMeasurement.VerticalMeasurementUnitOfMeasureID": null,
    "SpatialPoint.QuantitativeAccuracyBandID": null,
    "SpatialArea.QualitativeSpatialAccuracyTypeID": null,
    "SpatialArea.CoordinateQualityCheckPerformedBy": null,
    "VerticalMeasurement.VerticalReferenceEntityID": null,
    "SpatialPoint.SpatialGeometryTypeID": null,
    "ResourceHomeRegionID": null,
    "VerticalMeasurement.VerticalMeasurementSourceID": null,
    "IsDiscoverable": null,
    "VerticalMeasurement.VerticalReferenceID": null,
    "SubmitterName": null,
    "SpatialPoint.QualitativeSpatialAccuracyTypeID": null
  },
  "kind": "osdu:wks:work-product-component--WellboreMarkerSet:1.0.0",
  "source": "wks",
  "acl": {
    "viewers": [
      "data.default.viewers@contoso-data.dataservices.energy"
    ],
    "owners": [
      "data.default.owners@contoso-data.dataservices.energy"
    ]
  },
  "type": "work-product-component--WellboreMarkerSet",
  "version": 1678352411977404,
  "tags": null,
  "createTime": "2023-03-09T09:00:11.983Z",
  "authority": "osdu",
  "namespace": "osdu:wks",
  "legal": {
    "legaltags": [
      "contoso-data-open-test-data"
    ],
    "otherRelevantDataCountries": [
      "US"
    ],
    "status": "compliant"
  },
  "createUser": "a9b01ec8-23d6-41c6-8773-89cf40351b9a",
  "id": "contoso-data:work-product-component--WellboreMarkerSet:c2a87a257750415287d3fd0e75c6bbeb"
}