{
  "data": {
    "SpatialArea.QuantitativeAccuracyBandID": null,
    "Description": "Wellbore Marker",
    "ResourceLifecycleStatus": null,
    "SpatialArea.SpatialParameterTypeID": null,
    "ResourceCurationStatus": null,
    "TechnicalAssuranceID": null,
    "SpatialArea.SpatialGeometryTypeID": null,
    "Source": null,
    "IsExtendedLoad": null,
    "Name": "3136.csv",
    "Datasets": [
      "contoso-data:dataset--File.Generic:439979e3-9fd2-4fdc-8b9a-cc4838c115a0:1678349645290440"
    ],
    "VerticalMeasurement.VerticalCRSID": null,
    "VerticalMeasurement.VerticalMeasurementTypeID": null,
    "SpatialPoint.CoordinateQualityCheckPerformedBy": null,
    "ResourceSecurityClassification": "contoso-data:reference-data--ResourceSecurityClassification:RESTRICTED:",
    "VerticalMeasurement.WellboreTVDTrajectoryID": null,
    "VerticalMeasurement.VerticalMeasurementPathID": null,
    "ExistenceKind": null,
    "VerticalMeasurement.VerticalMeasurementDescription": null,
    "SpatialPoint.SpatialParameterTypeID": null,
    "Markers": [
      {
        "Missing": null,
        "MarkerMeasuredDepth": 0.0,
        "FeatureTypeID": null,
        "MarkerTypeID": null,
        "GeologicalAge": null,
        "MarkerInterpreter": null,
        "MarkerName": "North Sea Supergroup",
        "FeatureName": null
      },
      {
        "Missing": null,
        "MarkerMeasuredDepth": 352.0,
        "FeatureTypeID": null,
        "MarkerTypeID": null,
        "GeologicalAge": null,
        "MarkerInterpreter": null,
        "MarkerName": "Ommelanden Formation",
        "FeatureName": null
      },
      {
        "Missing": null,
        "MarkerMeasuredDepth": 531.0,
        "FeatureTypeID": null,
        "MarkerTypeID": null,
        "GeologicalAge": null,
        "MarkerInterpreter": null,
        "MarkerName": "Texel Marlstone Member",
        "FeatureName": null
      },
      {
        "Missing": null,
        "MarkerMeasuredDepth": 627.0,
        "FeatureTypeID": null,
        "MarkerTypeID": null,
        "GeologicalAge": null,
        "MarkerInterpreter": null,
        "MarkerName": "Holland Formation",
        "FeatureName": null
      },
      {
        "Missing": null,
        "MarkerMeasuredDepth": 801.0,
        "FeatureTypeID": null,
        "MarkerTypeID": null,
        "GeologicalAge": null,
        "MarkerInterpreter": null,
        "MarkerName": "Gildehaus Sandstone Member",
        "FeatureName": null
      },
      {
        "Missing": null,
        "MarkerMeasuredDepth": 821.5,
        "FeatureTypeID": null,
        "MarkerTypeID": null,
        "GeologicalAge": null,
        "MarkerInterpreter": null,
        "MarkerName": "Schoonebeek Member",
        "FeatureName": null
      },
      {
        "Missing": null,
        "MarkerMeasuredDepth": 833.5,
        "FeatureTypeID": null,
        "MarkerTypeID": null,
        "GeologicalAge": null,
        "MarkerInterpreter": null,
        "MarkerName": "Bentheim Sandstone Member",
        "FeatureName": null
      }
    ],
    "WellboreID": "contoso-data:master-data--Wellbore:3136:",
    "VerticalMeasurement.VerticalMeasurementUnitOfMeasureID": null,
    "SpatialPoint.QuantitativeAccuracyBandID": null,
    "SpatialArea.QualitativeSpatialAccuracyTypeID": null,
    "SpatialArea.CoordinateQualityCheckPerformedBy": null,
    "VerticalMeasurement.VerticalReferenceEntityID": null,
    "SpatialPoint.SpatialGeometryTypeID": null,
    "ResourceHomeRegionID": null,
    "VerticalMeasurement.VerticalMeasurementSourceID": null,
    "IsDiscoverable": null,
    "VerticalMeasurement.VerticalReferenceID": null,
    "SubmitterName": null,
    "SpatialPoint.QualitativeSpatialAccuracyTypeID": null
  },
  "kind": "osdu:wks:work-product-component--WellboreMarkerSet:1.0.0",
  "source": "wks",
  "acl": {
    "viewers": [
      "data.default.viewers@contoso-data.dataservices.energy"
    ],
    "owners": [
      "data.default.owners@contoso-data.dataservices.energy"
    ]
  },
  "type": "work-product-component--WellboreMarkerSet",
  "version": 1678352061044655,
  "tags": null,
  "createTime": "2023-03-09T08:54:21.052Z",
  "authority": "osdu",
  "namespace": "osdu:wks",
  "legal": {
    "legaltags": [
      "contoso-data-open-test-data"
    ],
    "otherRelevantDataCountries": [
      "US"
    ],
    "status": "compliant"
  },
  "createUser": "a9b01ec8-23d6-41c6-8773-89cf40351b9a",
  "id": "contoso-data:work-product-component--WellboreMarkerSet:aae95ba0a10348fa806f3e0eda9076b8"
}