{
  "data": {
    "SpatialArea.QuantitativeAccuracyBandID": null,
    "Description": "Wellbore Marker",
    "ResourceLifecycleStatus": null,
    "SpatialArea.SpatialParameterTypeID": null,
    "ResourceCurationStatus": null,
    "TechnicalAssuranceID": null,
    "SpatialArea.SpatialGeometryTypeID": null,
    "Source": null,
    "IsExtendedLoad": null,
    "Name": "1471.csv",
    "Datasets": [
      "contoso-data:dataset--File.Generic:88d5afcc-23b3-4be0-9d58-2ea53bbb5288:1678349571509665"
    ],
    "VerticalMeasurement.VerticalCRSID": null,
    "VerticalMeasurement.VerticalMeasurementTypeID": null,
    "SpatialPoint.CoordinateQualityCheckPerformedBy": null,
    "ResourceSecurityClassification": "contoso-data:reference-data--ResourceSecurityClassification:RESTRICTED:",
    "VerticalMeasurement.WellboreTVDTrajectoryID": null,
    "VerticalMeasurement.VerticalMeasurementPathID": null,
    "ExistenceKind": null,
    "VerticalMeasurement.VerticalMeasurementDescription": null,
    "SpatialPoint.SpatialParameterTypeID": null,
    "Markers": [
      {
        "Missing": null,
        "MarkerMeasuredDepth": 0.0,
        "FeatureTypeID": null,
        "MarkerTypeID": null,
        "GeologicalAge": null,
        "MarkerInterpreter": null,
        "MarkerName": "QUATER. UNDIFF.",
        "FeatureName": null
      },
      {
        "Missing": null,
        "MarkerMeasuredDepth": 155.0,
        "FeatureTypeID": null,
        "MarkerTypeID": null,
        "GeologicalAge": null,
        "MarkerInterpreter": null,
        "MarkerName": "Maassluis Formation",
        "FeatureName": null
      },
      {
        "Missing": null,
        "MarkerMeasuredDepth": 285.0,
        "FeatureTypeID": null,
        "MarkerTypeID": null,
        "GeologicalAge": null,
        "MarkerInterpreter": null,
        "MarkerName": "Oosterhout Formation",
        "FeatureName": null
      },
      {
        "Missing": null,
        "MarkerMeasuredDepth": 570.0,
        "FeatureTypeID": null,
        "MarkerTypeID": null,
        "GeologicalAge": null,
        "MarkerInterpreter": null,
        "MarkerName": "Breda Formation",
        "FeatureName": null
      },
      {
        "Missing": null,
        "MarkerMeasuredDepth": 710.0,
        "FeatureTypeID": null,
        "MarkerTypeID": null,
        "GeologicalAge": null,
        "MarkerInterpreter": null,
        "MarkerName": "Veldhoven Formation",
        "FeatureName": null
      },
      {
        "Missing": null,
        "MarkerMeasuredDepth": 809.0,
        "FeatureTypeID": null,
        "MarkerTypeID": null,
        "GeologicalAge": null,
        "MarkerInterpreter": null,
        "MarkerName": "Rupel Formation",
        "FeatureName": null
      },
      {
        "Missing": null,
        "MarkerMeasuredDepth": 915.0,
        "FeatureTypeID": null,
        "MarkerTypeID": null,
        "GeologicalAge": null,
        "MarkerInterpreter": null,
        "MarkerName": "Aalburg Formation",
        "FeatureName": null
      },
      {
        "Missing": null,
        "MarkerMeasuredDepth": 1058.0,
        "FeatureTypeID": null,
        "MarkerTypeID": null,
        "GeologicalAge": null,
        "MarkerInterpreter": null,
        "MarkerName": "Sleen Formation",
        "FeatureName": null
      },
      {
        "Missing": null,
        "MarkerMeasuredDepth": 1090.0,
        "FeatureTypeID": null,
        "MarkerTypeID": null,
        "GeologicalAge": null,
        "MarkerInterpreter": null,
        "MarkerName": "Lower Muschelkalk Member",
        "FeatureName": null
      },
      {
        "Missing": null,
        "MarkerMeasuredDepth": 1141.0,
        "FeatureTypeID": null,
        "MarkerTypeID": null,
        "GeologicalAge": null,
        "MarkerInterpreter": null,
        "MarkerName": "Upper Röt Claystone Member",
        "FeatureName": null
      },
      {
        "Missing": null,
        "MarkerMeasuredDepth": 1166.0,
        "FeatureTypeID": null,
        "MarkerTypeID": null,
        "GeologicalAge": null,
        "MarkerInterpreter": null,
        "MarkerName": "FAULT",
        "FeatureName": null
      },
      {
        "Missing": null,
        "MarkerMeasuredDepth": 1166.0,
        "FeatureTypeID": null,
        "MarkerTypeID": null,
        "GeologicalAge": null,
        "MarkerInterpreter": null,
        "MarkerName": "Detfurth Claystone Member",
        "FeatureName": null
      },
      {
        "Missing": null,
        "MarkerMeasuredDepth": 1168.0,
        "FeatureTypeID": null,
        "MarkerTypeID": null,
        "GeologicalAge": null,
        "MarkerInterpreter": null,
        "MarkerName": "Lower Detfurth Sandstone Member",
        "FeatureName": null
      },
      {
        "Missing": null,
        "MarkerMeasuredDepth": 1181.0,
        "FeatureTypeID": null,
        "MarkerTypeID": null,
        "GeologicalAge": null,
        "MarkerInterpreter": null,
        "MarkerName": "Volpriehausen Clay-Siltstone Member",
        "FeatureName": null
      },
      {
        "Missing": null,
        "MarkerMeasuredDepth": 1268.0,
        "FeatureTypeID": null,
        "MarkerTypeID": null,
        "GeologicalAge": null,
        "MarkerInterpreter": null,
        "MarkerName": "Lower Volpriehausen Sandstone Member",
        "FeatureName": null
      },
      {
        "Missing": null,
        "MarkerMeasuredDepth": 1290.0,
        "FeatureTypeID": null,
        "MarkerTypeID": null,
        "GeologicalAge": null,
        "MarkerInterpreter": null,
        "MarkerName": "Rogenstein Member",
        "FeatureName": null
      },
      {
        "Missing": null,
        "MarkerMeasuredDepth": 1428.0,
        "FeatureTypeID": null,
        "MarkerTypeID": null,
        "GeologicalAge": null,
        "MarkerInterpreter": null,
        "MarkerName": "Main Claystone Member",
        "FeatureName": null
      },
      {
        "Missing": null,
        "MarkerMeasuredDepth": 1560.0,
        "FeatureTypeID": null,
        "MarkerTypeID": null,
        "GeologicalAge": null,
        "MarkerInterpreter": null,
        "MarkerName": "Zechstein Upper Claystone Formation",
        "FeatureName": null
      },
      {
        "Missing": null,
        "MarkerMeasuredDepth": 1567.0,
        "FeatureTypeID": null,
        "MarkerTypeID": null,
        "GeologicalAge": null,
        "MarkerInterpreter": null,
        "MarkerName": "Z3 Carbonate Member",
        "FeatureName": null
      },
      {
        "Missing": null,
        "MarkerMeasuredDepth": 1575.0,
        "FeatureTypeID": null,
        "MarkerTypeID": null,
        "GeologicalAge": null,
        "MarkerInterpreter": null,
        "MarkerName": "Grey Salt Clay Member",
        "FeatureName": null
      },
      {
        "Missing": null,
        "MarkerMeasuredDepth": 1577.0,
        "FeatureTypeID": null,
        "MarkerTypeID": null,
        "GeologicalAge": null,
        "MarkerInterpreter": null,
        "MarkerName": "Z2 Middle Claystone Member",
        "FeatureName": null
      },
      {
        "Missing": null,
        "MarkerMeasuredDepth": 1607.0,
        "FeatureTypeID": null,
        "MarkerTypeID": null,
        "GeologicalAge": null,
        "MarkerInterpreter": null,
        "MarkerName": "Z1 Middle Claystone Member",
        "FeatureName": null
      },
      {
        "Missing": null,
        "MarkerMeasuredDepth": 1625.0,
        "FeatureTypeID": null,
        "MarkerTypeID": null,
        "GeologicalAge": null,
        "MarkerInterpreter": null,
        "MarkerName": "Z1 Fringe Carbonate Member",
        "FeatureName": null
      },
      {
        "Missing": null,
        "MarkerMeasuredDepth": 1656.0,
        "FeatureTypeID": null,
        "MarkerTypeID": null,
        "GeologicalAge": null,
        "MarkerInterpreter": null,
        "MarkerName": "Z1 Lower Claystone Member",
        "FeatureName": null
      },
      {
        "Missing": null,
        "MarkerMeasuredDepth": 1659.5,
        "FeatureTypeID": null,
        "MarkerTypeID": null,
        "GeologicalAge": null,
        "MarkerInterpreter": null,
        "MarkerName": "Slochteren Formation",
        "FeatureName": null
      },
      {
        "Missing": null,
        "MarkerMeasuredDepth": 1787.0,
        "FeatureTypeID": null,
        "MarkerTypeID": null,
        "GeologicalAge": null,
        "MarkerInterpreter": null,
        "MarkerName": "Hellevoetsluis Formation",
        "FeatureName": null
      },
      {
        "Missing": null,
        "MarkerMeasuredDepth": 2211.0,
        "FeatureTypeID": null,
        "MarkerTypeID": null,
        "GeologicalAge": null,
        "MarkerInterpreter": null,
        "MarkerName": "Maurits Formation",
        "FeatureName": null
      },
      {
        "Missing": null,
        "MarkerMeasuredDepth": 2346.0,
        "FeatureTypeID": null,
        "MarkerTypeID": null,
        "GeologicalAge": null,
        "MarkerInterpreter": null,
        "MarkerName": "Ruurlo Formation",
        "FeatureName": null
      },
      {
        "Missing": null,
        "MarkerMeasuredDepth": 2555.0,
        "FeatureTypeID": null,
        "MarkerTypeID": null,
        "GeologicalAge": null,
        "MarkerInterpreter": null,
        "MarkerName": "REVERSE",
        "FeatureName": null
      },
      {
        "Missing": null,
        "MarkerMeasuredDepth": 2555.0,
        "FeatureTypeID": null,
        "MarkerTypeID": null,
        "GeologicalAge": null,
        "MarkerInterpreter": null,
        "MarkerName": "Muschelkalk Evaporite Member",
        "FeatureName": null
      },
      {
        "Missing": null,
        "MarkerMeasuredDepth": 2578.0,
        "FeatureTypeID": null,
        "MarkerTypeID": null,
        "GeologicalAge": null,
        "MarkerInterpreter": null,
        "MarkerName": "Lower Muschelkalk Member",
        "FeatureName": null
      },
      {
        "Missing": null,
        "MarkerMeasuredDepth": 2665.0,
        "FeatureTypeID": null,
        "MarkerTypeID": null,
        "GeologicalAge": null,
        "MarkerInterpreter": null,
        "MarkerName": "Upper Röt Claystone Member",
        "FeatureName": null
      },
      {
        "Missing": null,
        "MarkerMeasuredDepth": 2780.0,
        "FeatureTypeID": null,
        "MarkerTypeID": null,
        "GeologicalAge": null,
        "MarkerInterpreter": null,
        "MarkerName": "Main Röt Evaporite Member",
        "FeatureName": null
      },
      {
        "Missing": null,
        "MarkerMeasuredDepth": 2785.0,
        "FeatureTypeID": null,
        "MarkerTypeID": null,
        "GeologicalAge": null,
        "MarkerInterpreter": null,
        "MarkerName": "Solling Claystone Member",
        "FeatureName": null
      },
      {
        "Missing": null,
        "MarkerMeasuredDepth": 2796.0,
        "FeatureTypeID": null,
        "MarkerTypeID": null,
        "GeologicalAge": null,
        "MarkerInterpreter": null,
        "MarkerName": "Basal Solling Sandstone Member",
        "FeatureName": null
      },
      {
        "Missing": null,
        "MarkerMeasuredDepth": 2804.0,
        "FeatureTypeID": null,
        "MarkerTypeID": null,
        "GeologicalAge": null,
        "MarkerInterpreter": null,
        "MarkerName": "Volpriehausen Clay-Siltstone Member",
        "FeatureName": null
      },
      {
        "Missing": null,
        "MarkerMeasuredDepth": 2885.0,
        "FeatureTypeID": null,
        "MarkerTypeID": null,
        "GeologicalAge": null,
        "MarkerInterpreter": null,
        "MarkerName": "Lower Volpriehausen Sandstone Member",
        "FeatureName": null
      },
      {
        "Missing": null,
        "MarkerMeasuredDepth": 2910.0,
        "FeatureTypeID": null,
        "MarkerTypeID": null,
        "GeologicalAge": null,
        "MarkerInterpreter": null,
        "MarkerName": "Rogenstein Member",
        "FeatureName": null
      },
      {
        "Missing": null,
        "MarkerMeasuredDepth": 3032.0,
        "FeatureTypeID": null,
        "MarkerTypeID": null,
        "GeologicalAge": null,
        "MarkerInterpreter": null,
        "MarkerName": "Main Claystone Member",
        "FeatureName": null
      },
      {
        "Missing": null,
        "MarkerMeasuredDepth": 3151.0,
        "FeatureTypeID": null,
        "MarkerTypeID": null,
        "GeologicalAge": null,
        "MarkerInterpreter": null,
        "MarkerName": "Zechstein Upper Claystone Formation",
        "FeatureName": null
      },
      {
        "Missing": null,
        "MarkerMeasuredDepth": 3155.0,
        "FeatureTypeID": null,
        "MarkerTypeID": null,
        "GeologicalAge": null,
        "MarkerInterpreter": null,
        "MarkerName": "Z3 Carbonate Member",
        "FeatureName": null
      },
      {
        "Missing": null,
        "MarkerMeasuredDepth": 3165.0,
        "FeatureTypeID": null,
        "MarkerTypeID": null,
        "GeologicalAge": null,
        "MarkerInterpreter": null,
        "MarkerName": "Grey Salt Clay Member",
        "FeatureName": null
      },
      {
        "Missing": null,
        "MarkerMeasuredDepth": 3167.0,
        "FeatureTypeID": null,
        "MarkerTypeID": null,
        "GeologicalAge": null,
        "MarkerInterpreter": null,
        "MarkerName": "Z2 Middle Claystone Member",
        "FeatureName": null
      },
      {
        "Missing": null,
        "MarkerMeasuredDepth": 3192.0,
        "FeatureTypeID": null,
        "MarkerTypeID": null,
        "GeologicalAge": null,
        "MarkerInterpreter": null,
        "MarkerName": "Z1 Middle Claystone Member",
        "FeatureName": null
      },
      {
        "Missing": null,
        "MarkerMeasuredDepth": 3215.0,
        "FeatureTypeID": null,
        "MarkerTypeID": null,
        "GeologicalAge": null,
        "MarkerInterpreter": null,
        "MarkerName": "Z1 Fringe Carbonate Member",
        "FeatureName": null
      },
      {
        "Missing": null,
        "MarkerMeasuredDepth": 3240.0,
        "FeatureTypeID": null,
        "MarkerTypeID": null,
        "GeologicalAge": null,
        "MarkerInterpreter": null,
        "MarkerName": "Slochteren Formation",
        "FeatureName": null
      },
      {
        "Missing": null,
        "MarkerMeasuredDepth": 3378.0,
        "FeatureTypeID": null,
        "MarkerTypeID": null,
        "GeologicalAge": null,
        "MarkerInterpreter": null,
        "MarkerName": "Hellevoetsluis Formation",
        "FeatureName": null
      }
    ],
    "WellboreID": "contoso-data:master-data--Wellbore:1471:",
    "VerticalMeasurement.VerticalMeasurementUnitOfMeasureID": null,
    "SpatialPoint.QuantitativeAccuracyBandID": null,
    "SpatialArea.QualitativeSpatialAccuracyTypeID": null,
    "SpatialArea.CoordinateQualityCheckPerformedBy": null,
    "VerticalMeasurement.VerticalReferenceEntityID": null,
    "SpatialPoint.SpatialGeometryTypeID": null,
    "ResourceHomeRegionID": null,
    "VerticalMeasurement.VerticalMeasurementSourceID": null,
    "IsDiscoverable": null,
    "VerticalMeasurement.VerticalReferenceID": null,
    "SubmitterName": null,
    "SpatialPoint.QualitativeSpatialAccuracyTypeID": null
  },
  "kind": "osdu:wks:work-product-component--WellboreMarkerSet:1.0.0",
  "source": "wks",
  "acl": {
    "viewers": [
      "data.default.viewers@contoso-data.dataservices.energy"
    ],
    "owners": [
      "data.default.owners@contoso-data.dataservices.energy"
    ]
  },
  "type": "work-product-component--WellboreMarkerSet",
  "version": 1678351804000723,
  "tags": null,
  "createTime": "2023-03-09T08:50:04.006Z",
  "authority": "osdu",
  "namespace": "osdu:wks",
  "legal": {
    "legaltags": [
      "contoso-data-open-test-data"
    ],
    "otherRelevantDataCountries": [
      "US"
    ],
    "status": "compliant"
  },
  "createUser": "a9b01ec8-23d6-41c6-8773-89cf40351b9a",
  "id": "contoso-data:work-product-component--WellboreMarkerSet:d6db79a5d68444a285432ba52c17c312"
}