{
  "data": {
    "SpatialArea.QuantitativeAccuracyBandID": null,
    "Description": "Wellbore Marker",
    "ResourceLifecycleStatus": null,
    "SpatialArea.SpatialParameterTypeID": null,
    "ResourceCurationStatus": null,
    "TechnicalAssuranceID": null,
    "SpatialArea.SpatialGeometryTypeID": null,
    "Source": null,
    "IsExtendedLoad": null,
    "Name": "2344.csv",
    "Datasets": [
      "contoso-data:dataset--File.Generic:6f2b7f32-53a2-4092-8aba-97b5d39b4356:1678349607463723"
    ],
    "VerticalMeasurement.VerticalCRSID": null,
    "VerticalMeasurement.VerticalMeasurementTypeID": null,
    "SpatialPoint.CoordinateQualityCheckPerformedBy": null,
    "ResourceSecurityClassification": "contoso-data:reference-data--ResourceSecurityClassification:RESTRICTED:",
    "VerticalMeasurement.WellboreTVDTrajectoryID": null,
    "VerticalMeasurement.VerticalMeasurementPathID": null,
    "ExistenceKind": null,
    "VerticalMeasurement.VerticalMeasurementDescription": null,
    "SpatialPoint.SpatialParameterTypeID": null,
    "Markers": [
      {
        "Missing": null,
        "MarkerMeasuredDepth": 6.5,
        "FeatureTypeID": null,
        "MarkerTypeID": null,
        "GeologicalAge": null,
        "MarkerInterpreter": null,
        "MarkerName": "Upper North Sea Group",
        "FeatureName": null
      },
      {
        "Missing": null,
        "MarkerMeasuredDepth": 501.5,
        "FeatureTypeID": null,
        "MarkerTypeID": null,
        "GeologicalAge": null,
        "MarkerInterpreter": null,
        "MarkerName": "Rupel Clay Member",
        "FeatureName": null
      },
      {
        "Missing": null,
        "MarkerMeasuredDepth": 612.5,
        "FeatureTypeID": null,
        "MarkerTypeID": null,
        "GeologicalAge": null,
        "MarkerInterpreter": null,
        "MarkerName": "Rupel Formation",
        "FeatureName": null
      },
      {
        "Missing": null,
        "MarkerMeasuredDepth": 617.5,
        "FeatureTypeID": null,
        "MarkerTypeID": null,
        "GeologicalAge": null,
        "MarkerInterpreter": null,
        "MarkerName": "Asse Member",
        "FeatureName": null
      },
      {
        "Missing": null,
        "MarkerMeasuredDepth": 656.0,
        "FeatureTypeID": null,
        "MarkerTypeID": null,
        "GeologicalAge": null,
        "MarkerInterpreter": null,
        "MarkerName": "Brussels Sand Member",
        "FeatureName": null
      },
      {
        "Missing": null,
        "MarkerMeasuredDepth": 801.0,
        "FeatureTypeID": null,
        "MarkerTypeID": null,
        "GeologicalAge": null,
        "MarkerInterpreter": null,
        "MarkerName": "Ieper Member",
        "FeatureName": null
      },
      {
        "Missing": null,
        "MarkerMeasuredDepth": 967.0,
        "FeatureTypeID": null,
        "MarkerTypeID": null,
        "GeologicalAge": null,
        "MarkerInterpreter": null,
        "MarkerName": "Basal Dongen Tuffite Member",
        "FeatureName": null
      },
      {
        "Missing": null,
        "MarkerMeasuredDepth": 988.5,
        "FeatureTypeID": null,
        "MarkerTypeID": null,
        "GeologicalAge": null,
        "MarkerInterpreter": null,
        "MarkerName": "Landen Clay Member",
        "FeatureName": null
      },
      {
        "Missing": null,
        "MarkerMeasuredDepth": 999.5,
        "FeatureTypeID": null,
        "MarkerTypeID": null,
        "GeologicalAge": null,
        "MarkerInterpreter": null,
        "MarkerName": "Chalk Group",
        "FeatureName": null
      },
      {
        "Missing": null,
        "MarkerMeasuredDepth": 1478.0,
        "FeatureTypeID": null,
        "MarkerTypeID": null,
        "GeologicalAge": null,
        "MarkerInterpreter": null,
        "MarkerName": "Upper Holland Marl Member",
        "FeatureName": null
      },
      {
        "Missing": null,
        "MarkerMeasuredDepth": 1513.5,
        "FeatureTypeID": null,
        "MarkerTypeID": null,
        "GeologicalAge": null,
        "MarkerInterpreter": null,
        "MarkerName": "Vlieland Claystone Formation",
        "FeatureName": null
      },
      {
        "Missing": null,
        "MarkerMeasuredDepth": 1528.0,
        "FeatureTypeID": null,
        "MarkerTypeID": null,
        "GeologicalAge": null,
        "MarkerInterpreter": null,
        "MarkerName": "Main Claystone Member",
        "FeatureName": null
      },
      {
        "Missing": null,
        "MarkerMeasuredDepth": 1711.0,
        "FeatureTypeID": null,
        "MarkerTypeID": null,
        "GeologicalAge": null,
        "MarkerInterpreter": null,
        "MarkerName": "Lower Buntsandstein Formation",
        "FeatureName": null
      },
      {
        "Missing": null,
        "MarkerMeasuredDepth": 1737.0,
        "FeatureTypeID": null,
        "MarkerTypeID": null,
        "GeologicalAge": null,
        "MarkerInterpreter": null,
        "MarkerName": "Z4 Salt Member",
        "FeatureName": null
      },
      {
        "Missing": null,
        "MarkerMeasuredDepth": 1864.0,
        "FeatureTypeID": null,
        "MarkerTypeID": null,
        "GeologicalAge": null,
        "MarkerInterpreter": null,
        "MarkerName": "Z3 Salt Member",
        "FeatureName": null
      },
      {
        "Missing": null,
        "MarkerMeasuredDepth": 2623.0,
        "FeatureTypeID": null,
        "MarkerTypeID": null,
        "GeologicalAge": null,
        "MarkerInterpreter": null,
        "MarkerName": "Z2 Basal Anhydrite Member",
        "FeatureName": null
      },
      {
        "Missing": null,
        "MarkerMeasuredDepth": 2628.0,
        "FeatureTypeID": null,
        "MarkerTypeID": null,
        "GeologicalAge": null,
        "MarkerInterpreter": null,
        "MarkerName": "Z2 Carbonate Member",
        "FeatureName": null
      },
      {
        "Missing": null,
        "MarkerMeasuredDepth": 2642.0,
        "FeatureTypeID": null,
        "MarkerTypeID": null,
        "GeologicalAge": null,
        "MarkerInterpreter": null,
        "MarkerName": "Z1 Middle Claystone Member",
        "FeatureName": null
      },
      {
        "Missing": null,
        "MarkerMeasuredDepth": 2671.0,
        "FeatureTypeID": null,
        "MarkerTypeID": null,
        "GeologicalAge": null,
        "MarkerInterpreter": null,
        "MarkerName": "Z1 Carbonate Member",
        "FeatureName": null
      },
      {
        "Missing": null,
        "MarkerMeasuredDepth": 2680.0,
        "FeatureTypeID": null,
        "MarkerTypeID": null,
        "GeologicalAge": null,
        "MarkerInterpreter": null,
        "MarkerName": "Coppershale Member",
        "FeatureName": null
      },
      {
        "Missing": null,
        "MarkerMeasuredDepth": 2681.0,
        "FeatureTypeID": null,
        "MarkerTypeID": null,
        "GeologicalAge": null,
        "MarkerInterpreter": null,
        "MarkerName": "Ten Boer Member",
        "FeatureName": null
      },
      {
        "Missing": null,
        "MarkerMeasuredDepth": 2736.5,
        "FeatureTypeID": null,
        "MarkerTypeID": null,
        "GeologicalAge": null,
        "MarkerInterpreter": null,
        "MarkerName": "Slochteren Formation",
        "FeatureName": null
      },
      {
        "Missing": null,
        "MarkerMeasuredDepth": 2911.0,
        "FeatureTypeID": null,
        "MarkerTypeID": null,
        "GeologicalAge": null,
        "MarkerInterpreter": null,
        "MarkerName": "Tubbergen Formation",
        "FeatureName": null
      },
      {
        "Missing": null,
        "MarkerMeasuredDepth": 3028.0,
        "FeatureTypeID": null,
        "MarkerTypeID": null,
        "GeologicalAge": null,
        "MarkerInterpreter": null,
        "MarkerName": "Maurits Formation",
        "FeatureName": null
      }
    ],
    "WellboreID": "contoso-data:master-data--Wellbore:2344:",
    "VerticalMeasurement.VerticalMeasurementUnitOfMeasureID": null,
    "SpatialPoint.QuantitativeAccuracyBandID": null,
    "SpatialArea.QualitativeSpatialAccuracyTypeID": null,
    "SpatialArea.CoordinateQualityCheckPerformedBy": null,
    "VerticalMeasurement.VerticalReferenceEntityID": null,
    "SpatialPoint.SpatialGeometryTypeID": null,
    "ResourceHomeRegionID": null,
    "VerticalMeasurement.VerticalMeasurementSourceID": null,
    "IsDiscoverable": null,
    "VerticalMeasurement.VerticalReferenceID": null,
    "SubmitterName": null,
    "SpatialPoint.QualitativeSpatialAccuracyTypeID": null
  },
  "kind": "osdu:wks:work-product-component--WellboreMarkerSet:1.0.0",
  "source": "wks",
  "acl": {
    "viewers": [
      "data.default.viewers@contoso-data.dataservices.energy"
    ],
    "owners": [
      "data.default.owners@contoso-data.dataservices.energy"
    ]
  },
  "type": "work-product-component--WellboreMarkerSet",
  "version": 1678351932375095,
  "tags": null,
  "createTime": "2023-03-09T08:52:12.384Z",
  "authority": "osdu",
  "namespace": "osdu:wks",
  "legal": {
    "legaltags": [
      "contoso-data-open-test-data"
    ],
    "otherRelevantDataCountries": [
      "US"
    ],
    "status": "compliant"
  },
  "createUser": "a9b01ec8-23d6-41c6-8773-89cf40351b9a",
  "id": "contoso-data:work-product-component--WellboreMarkerSet:e6e390d0c8f44e3cb27775ccd02c7b90"
}