{
  "data": {
    "SpatialArea.QuantitativeAccuracyBandID": null,
    "SpatialArea.SpatialParameterTypeID": null,
    "ResourceCurationStatus": null,
    "SpatialArea.SpatialGeometryTypeID": null,
    "IsExtendedLoad": null,
    "Name": "3844_ten01_1992_comp.las",
    "Datasets": [
      "contoso-data:dataset--File.Generic:7fb695b3-a580-44db-b35b-59a58ebebf79:1678349515928450"
    ],
    "VerticalMeasurement.VerticalCRSID": null,
    "ResourceSecurityClassification": "contoso-data:reference-data--ResourceSecurityClassification:RESTRICTED:",
    "VerticalMeasurement.VerticalMeasurementPathID": null,
    "ExistenceKind": null,
    "HoleTypeLogging": null,
    "LoggingDirection": null,
    "VerticalMeasurementID": null,
    "SpatialArea.QualitativeSpatialAccuracyTypeID": null,
    "VerticalMeasurement.VerticalReferenceEntityID": null,
    "SpatialPoint.SpatialGeometryTypeID": null,
    "VerticalMeasurement.VerticalMeasurementSourceID": null,
    "WellLogTypeID": null,
    "IsDiscoverable": null,
    "LoggingService": null,
    "VerticalMeasurement.VerticalReferenceID": null,
    "SubmitterName": null,
    "LogRun": null,
    "SpatialPoint.QualitativeSpatialAccuracyTypeID": null,
    "LogActivity": null,
    "Description": "Well Log",
    "ResourceLifecycleStatus": null,
    "TopMeasuredDepth": 2643.3004,
    "ServiceCompanyID": null,
    "TechnicalAssuranceID": null,
    "Source": null,
    "LogVersion": null,
    "VerticalMeasurement.VerticalMeasurementTypeID": null,
    "LogSource": null,
    "ToolStringDescription": null,
    "SpatialPoint.CoordinateQualityCheckPerformedBy": null,
    "DrillingFluidProperty": null,
    "VerticalMeasurement.WellboreTVDTrajectoryID": null,
    "VerticalMeasurement.VerticalMeasurementDescription": null,
    "SpatialPoint.SpatialParameterTypeID": null,
    "WellboreID": "contoso-data:master-data--Wellbore:3844:",
    "ActivityType": null,
    "VerticalMeasurement.VerticalMeasurementUnitOfMeasureID": null,
    "SpatialPoint.QuantitativeAccuracyBandID": null,
    "SpatialArea.CoordinateQualityCheckPerformedBy": null,
    "ResourceHomeRegionID": null,
    "BottomMeasuredDepth": 2934.4,
    "Curves": [
      {
        "IsProcessed": null,
        "LogCurveMainFamilyID": null,
        "LogCurveFamilyID": null,
        "CurveID": null,
        "TopDepth": 2643.3,
        "CurveVersion": null,
        "InterpreterName": null,
        "CurveQuality": null,
        "NullValue": null,
        "Interpolate": null,
        "DepthUnit": "contoso-data:reference-data--UnitOfMeasure:M:",
        "DepthCoding": null,
        "Mnemonic": "DEPT",
        "BaseDepth": 2934.4,
        "LogCurveTypeID": null,
        "LogCurveBusinessValueID": null,
        "CurveUnit": "contoso-data:reference-data--UnitOfMeasure:M:"
      },
      {
        "IsProcessed": null,
        "LogCurveMainFamilyID": null,
        "LogCurveFamilyID": null,
        "CurveID": null,
        "TopDepth": 2643.3,
        "CurveVersion": null,
        "InterpreterName": null,
        "CurveQuality": null,
        "NullValue": null,
        "Interpolate": null,
        "DepthUnit": "contoso-data:reference-data--UnitOfMeasure:M:",
        "DepthCoding": null,
        "Mnemonic": "GR",
        "BaseDepth": 2934.4,
        "LogCurveTypeID": null,
        "LogCurveBusinessValueID": null,
        "CurveUnit": "contoso-data:reference-data--UnitOfMeasure:GAPI:"
      },
      {
        "IsProcessed": null,
        "LogCurveMainFamilyID": null,
        "LogCurveFamilyID": null,
        "CurveID": null,
        "TopDepth": 2643.3,
        "CurveVersion": null,
        "InterpreterName": null,
        "CurveQuality": null,
        "NullValue": null,
        "Interpolate": null,
        "DepthUnit": "contoso-data:reference-data--UnitOfMeasure:M:",
        "DepthCoding": null,
        "Mnemonic": "DT",
        "BaseDepth": 2934.4,
        "LogCurveTypeID": null,
        "LogCurveBusinessValueID": null,
        "CurveUnit": "contoso-data:reference-data--UnitOfMeasure:US%2FF:"
      },
      {
        "IsProcessed": null,
        "LogCurveMainFamilyID": null,
        "LogCurveFamilyID": null,
        "CurveID": null,
        "TopDepth": 2643.3,
        "CurveVersion": null,
        "InterpreterName": null,
        "CurveQuality": null,
        "NullValue": null,
        "Interpolate": null,
        "DepthUnit": "contoso-data:reference-data--UnitOfMeasure:M:",
        "DepthCoding": null,
        "Mnemonic": "RHOB",
        "BaseDepth": 2934.4,
        "LogCurveTypeID": null,
        "LogCurveBusinessValueID": null,
        "CurveUnit": "contoso-data:reference-data--UnitOfMeasure:G%2FC3:"
      },
      {
        "IsProcessed": null,
        "LogCurveMainFamilyID": null,
        "LogCurveFamilyID": null,
        "CurveID": null,
        "TopDepth": 2643.3,
        "CurveVersion": null,
        "InterpreterName": null,
        "CurveQuality": null,
        "NullValue": null,
        "Interpolate": null,
        "DepthUnit": "contoso-data:reference-data--UnitOfMeasure:M:",
        "DepthCoding": null,
        "Mnemonic": "DRHO",
        "BaseDepth": 2934.4,
        "LogCurveTypeID": null,
        "LogCurveBusinessValueID": null,
        "CurveUnit": "contoso-data:reference-data--UnitOfMeasure:G%2FC3:"
      },
      {
        "IsProcessed": null,
        "LogCurveMainFamilyID": null,
        "LogCurveFamilyID": null,
        "CurveID": null,
        "TopDepth": 2643.3,
        "CurveVersion": null,
        "InterpreterName": null,
        "CurveQuality": null,
        "NullValue": null,
        "Interpolate": null,
        "DepthUnit": "contoso-data:reference-data--UnitOfMeasure:M:",
        "DepthCoding": null,
        "Mnemonic": "NPHI",
        "BaseDepth": 2934.4,
        "LogCurveTypeID": null,
        "LogCurveBusinessValueID": null,
        "CurveUnit": "contoso-data:reference-data--UnitOfMeasure:V%2FV:"
      }
    ]
  },
  "kind": "osdu:wks:work-product-component--WellLog:1.0.0",
  "source": "wks",
  "acl": {
    "viewers": [
      "data.default.viewers@contoso-data.dataservices.energy"
    ],
    "owners": [
      "data.default.owners@contoso-data.dataservices.energy"
    ]
  },
  "type": "work-product-component--WellLog",
  "version": 1678353993734111,
  "tags": null,
  "createTime": "2023-03-09T09:26:33.74Z",
  "authority": "osdu",
  "namespace": "osdu:wks",
  "legal": {
    "legaltags": [
      "contoso-data-open-test-data"
    ],
    "otherRelevantDataCountries": [
      "US"
    ],
    "status": "compliant"
  },
  "createUser": "a9b01ec8-23d6-41c6-8773-89cf40351b9a",
  "id": "contoso-data:work-product-component--WellLog:13cd089e29054df89f83ae83d2d24a92"
}